pot-0.9.6.post1.dist-info/RECORD
pot-0.9.6.post1.dist-info/WHEEL
pot-0.9.6.post1.dist-info/top_level.txt
pot-0.9.6.post1.dist-info/METADATA
pot-0.9.6.post1.dist-info/licenses/LICENSE
ot/coot.py
ot/gmm.py
ot/plot.py
ot/backend.py
ot/stochastic.py
ot/datasets.py
ot/__init__.py
ot/solvers.py
ot/lowrank.py
ot/dr.py
ot/regpath.py
ot/utils.py
ot/smooth.py
ot/sliced.py
ot/mapping.py
ot/optim.py
ot/factored.py
ot/gaussian.py
ot/weak.py
ot/da.py
ot/bregman/_screenkhorn.py
ot/bregman/_barycenter.py
ot/bregman/__init__.py
ot/bregman/_empirical.py
ot/bregman/_geomloss.py
ot/bregman/_dictionary.py
ot/bregman/_sinkhorn.py
ot/bregman/_convolutional.py
ot/bregman/_utils.py
ot/partial/partial_solvers.py
ot/partial/__init__.py
ot/partial/partial_cython.cpython-312-darwin.so
ot/lp/dmmot.py
ot/lp/emd_wrap.cpython-312-darwin.so
ot/lp/_barycenter_solvers.py
ot/lp/__init__.py
ot/lp/_network_simplex.py
ot/lp/cvx.py
ot/lp/solver_1d.py
ot/gnn/_layers.py
ot/gnn/__init__.py
ot/gnn/_utils.py
ot/gromov/_bregman.py
ot/gromov/_unbalanced.py
ot/gromov/__init__.py
ot/gromov/_quantized.py
ot/gromov/_lowrank.py
ot/gromov/_semirelaxed.py
ot/gromov/_estimators.py
ot/gromov/_dictionary.py
ot/gromov/_gw.py
ot/gromov/_partial.py
ot/gromov/_utils.py
ot/batch/__init__.py
ot/batch/_quadratic.py
ot/batch/_linear.py
ot/batch/_utils.py
ot/unbalanced/__init__.py
ot/unbalanced/_mm.py
ot/unbalanced/_sinkhorn.py
ot/unbalanced/_lbfgs.py
ot/helpers/openmp_helpers.py
ot/helpers/__init__.py
ot/helpers/pre_build_helpers.py
