Metadata-Version: 2.4
Name: POT
Version: 0.9.6.post1
Summary: Python Optimal Transport Library
Home-page: https://github.com/PythonOT/POT
Download-URL: https://github.com/PythonOT/POT/archive/0.9.6.post1.tar.gz
Author: Remi Flamary, Nicolas Courty, Cédric Vincent-Cuaz, POT Contributors
Author-email: remi.flamary@gmail.com, ncourty@gmail.com, cedvincentcuaz@gmail.com
License: MIT
Platform: linux
Platform: macosx
Platform: windows
Classifier: Development Status :: 5 - Production/Stable
Classifier: Intended Audience :: Developers
Classifier: Intended Audience :: Education
Classifier: Intended Audience :: Science/Research
Classifier: License :: OSI Approved :: MIT License
Classifier: Environment :: Console
Classifier: Operating System :: OS Independent
Classifier: Operating System :: POSIX :: Linux
Classifier: Operating System :: MacOS
Classifier: Operating System :: POSIX
Classifier: Operating System :: Microsoft :: Windows
Classifier: Programming Language :: Python
Classifier: Programming Language :: C++
Classifier: Programming Language :: C
Classifier: Programming Language :: Cython
Classifier: Topic :: Utilities
Classifier: Topic :: Scientific/Engineering :: Artificial Intelligence
Classifier: Topic :: Scientific/Engineering :: Mathematics
Classifier: Topic :: Scientific/Engineering :: Information Analysis
Classifier: Programming Language :: Python :: 3
Classifier: Programming Language :: Python :: 3.7
Classifier: Programming Language :: Python :: 3.8
Classifier: Programming Language :: Python :: 3.9
Classifier: Programming Language :: Python :: 3.10
Classifier: Programming Language :: Python :: 3.11
Classifier: Programming Language :: Python :: 3.12
Requires-Python: >=3.7
License-File: LICENSE
Requires-Dist: numpy>=1.16
Requires-Dist: scipy>=1.6
Provides-Extra: backend-numpy
Provides-Extra: backend-jax
Requires-Dist: jax; extra == "backend-jax"
Requires-Dist: jaxlib; extra == "backend-jax"
Provides-Extra: backend-cupy
Provides-Extra: backend-tf
Requires-Dist: tensorflow; extra == "backend-tf"
Provides-Extra: backend-torch
Requires-Dist: torch; extra == "backend-torch"
Provides-Extra: cvxopt
Requires-Dist: cvxopt; extra == "cvxopt"
Provides-Extra: dr
Requires-Dist: scikit-learn; extra == "dr"
Requires-Dist: pymanopt; extra == "dr"
Requires-Dist: autograd; extra == "dr"
Provides-Extra: gnn
Requires-Dist: torch; extra == "gnn"
Requires-Dist: torch_geometric; extra == "gnn"
Provides-Extra: plot
Requires-Dist: matplotlib; extra == "plot"
Provides-Extra: all
Requires-Dist: jax; extra == "all"
Requires-Dist: jaxlib; extra == "all"
Requires-Dist: tensorflow; extra == "all"
Requires-Dist: torch; extra == "all"
Requires-Dist: cvxopt; extra == "all"
Requires-Dist: scikit-learn; extra == "all"
Requires-Dist: pymanopt; extra == "all"
Requires-Dist: autograd; extra == "all"
Requires-Dist: torch_geometric; extra == "all"
Requires-Dist: matplotlib; extra == "all"
Dynamic: author
Dynamic: author-email
Dynamic: classifier
Dynamic: description
Dynamic: description-content-type
Dynamic: download-url
Dynamic: home-page
Dynamic: license
Dynamic: license-file
Dynamic: platform
Dynamic: provides-extra
Dynamic: requires-dist
Dynamic: requires-python
Dynamic: summary
